<?xml version="1.0" encoding="utf-8"?>
<!DOCTYPE hibernate-mapping PUBLIC "-//Hibernate/Hibernate Mapping DTD 3.0//EN"
"http://hibernate.sourceforge.net/hibernate-mapping-3.0.dtd">
<!-- 
    Mapping file autogenerated by MyEclipse Persistence Tools
-->
<hibernate-mapping>
    <class name="com.boyue.spa.domain.Vodpart" table="vodpart" >
        <id name="id" type="java.lang.Integer">
            <column name="id" />
            <generator class="identity" />
        </id>
        <property name="vodpartname" type="java.lang.String">
            <column name="vodpartname" length="30">
                <comment>栏目名称</comment>
            </column>
        </property>
        <property name="vodpartnamee" type="java.lang.String">
            <column name="vodpartnamee" length="30" >
                <comment>英文栏目名称</comment>
            </column>
        </property>
         <property name="vodpartname_jap" type="java.lang.String">
            <column name="vodpartname_jap" length="30" >
            </column>
        </property>
         <property name="vodpartname_kor" type="java.lang.String">
            <column name="vodpartname_kor" length="30" >
            </column>
        </property>
        <property name="img" type="java.lang.String">
            <column name="img" length="100" not-null="true">
                <comment>图片</comment>
            </column>
        </property>
        <property name="partintr" type="java.lang.String">
            <column name="partintr">
                <comment>栏目简介</comment>
            </column>
        </property>
        <property name="xmlpath" type="java.lang.String">
            <column name="xmlpath" />
        </property>
    </class>
</hibernate-mapping>
