<?xml version="1.0" encoding="utf-8"?>
<!DOCTYPE hibernate-mapping PUBLIC "-//Hibernate/Hibernate Mapping DTD 3.0//EN"
"http://hibernate.sourceforge.net/hibernate-mapping-3.0.dtd">
<!-- 
    Mapping file autogenerated by MyEclipse Persistence Tools
-->
<hibernate-mapping>
    <class name="com.boyue.spa.domain.Vodvideo" table="vodvideo" >
        <id name="id" type="java.lang.Integer">
            <column name="id" />
            <generator class="identity" />
        </id>
        <property name="vodprogramid" type="java.lang.Integer">
            <column name="vodprogramid" not-null="true">
                <comment>二级视频栏目id</comment>
            </column> 
        </property>
        <property name="voidname" type="java.lang.String">
            <column name="voidname" length="50" not-null="true">
                <comment>点播视频名称</comment>
            </column>
        </property>
        <property name="voidnamee" type="java.lang.String">
            <column name="voidnamee" length="50" not-null="true">
                <comment>点播视频名称</comment>
            </column>
        </property>
        <property name="voidpath" type="java.lang.String">
            <column name="voidpath" not-null="true">
                <comment>点播视频路径</comment>
            </column>
        </property>
        <property name="voidformat" type="java.lang.String">
            <column name="voidformat" length="50"  >
                <comment>点播文件格式</comment>
            </column>
        </property>
        <property name="voidgrade" type="java.lang.String">
            <column name="voidgrade" length="50"  >
                <comment>视频等级</comment>
            </column>
        </property>
        <property name="serverid" type="java.lang.String">
            <column name="serverid"  >
                <comment>服务器地址</comment>
            </column>
        </property>
        <property name="filmid" type="java.lang.String">
            <column name="filmid">
                <comment>加密后视频ID</comment>
            </column>
        </property>
        <property name="servername" type="java.lang.String">
            <column name="servername">
                <comment>服务器名称</comment>
            </column>
        </property>
        <property name="voidstatus" type="java.lang.Integer">
            <column name="voidstatus"  >
                <comment>点播状态(1启用，0停用)</comment>
            </column>
        </property>
        <property name="ifenable" type="java.lang.Integer">
            <column name="ifenable" not-null="true">
                <comment>是否发布</comment>
            </column>
        </property>
        <property name="releasetype" type="java.lang.Integer">
            <column name="releasetype">
                <comment>发布类型(自动1，手动0)</comment>
            </column>
        </property>
        <property name="createtime" type="java.util.Date">
            <column name="createtime" length="19" not-null="true">
                <comment>创建时间</comment>
            </column>
        </property>
        <property name="releasetime" type="java.util.Date">
            <column name="releasetime" length="19">
                <comment>发布时间</comment>
            </column>
        </property>
        <property name="createadmin" type="java.lang.String">
            <column name="createadmin" length="50" not-null="true">
                <comment>创建人</comment>
            </column>
        </property>
        <property name="position" type="java.lang.Integer">
            <column name="position">
                <comment>顺序</comment>
            </column>
        </property>
    </class>
</hibernate-mapping>
